{
    "data": {
        "event": {
            "id": "5c4710ed-e365-4f0a-971b-b268db4f9fb8",
            "picture": "https://services.medicalcongress.online/congress/medias/2023/JFR-2023/1940/video/thumbs/poster.jpg",
            "title": "La financiarisation de la radiologie : mutations inéluctables ou démédicalisation dangereuse ?",
            "start": "2023-10-14T16:40+02:00",
            "end": "2023-10-14T17:30+02:00",
            "objectives": [],
            "vod": {
                "checkPermissions": [
                    "media:view"
                ],
                "media": null
            },
            "schedule": {
                "items": [
                    {
                        "id": "42a36173-54e6-4b8d-aa43-09f4fe46790a",
                        "title": "La financiarisation de la radiologie : mutations inéluctables ou démédicalisation dangereuse ?",
                        "start": "2023-10-14T16:40+02:00",
                        "end": "2023-10-14T17:30+02:00",
                        "speakers": {
                            "items": []
                        },
                        "vod": {
                            "checkPermissions": [
                                "media:view"
                            ],
                            "media": {
                                "id": "c721e7fc-5916-424b-9b06-4d6184c571ad",
                                "type": "VIDEO",
                                "thumbnail": "https://services.medicalcongress.online/congress/medias/2023/JFR-2023/1940/video/thumbs/poster.jpg",
                                "element": {
                                    "sources": [
                                        {
                                            "uri": "https://services.medicalcongress.online/congress/medias/2023/JFR-2023/1940/video/y_1080p_4000kb.mp4"
                                        },
                                        {
                                            "uri": "https://services.medicalcongress.online/congress/medias/2023/JFR-2023/1940/video/y_480p_800kb.mp4"
                                        }
                                    ]
                                }
                            }
                        }
                    }
                ]
            }
        }
    }
}