{"data": {"event": {"id": "605d4b2c-22f1-45ea-b734-4f993c70f924", "picture": "https://services.medicalcongress.online/congress/medias/2023/JFR-2023/1465/video/thumbs/poster.jpg", "title": "Journée CERF-FLI : Impacts organisationnels des dépistages", "start": "2023-10-12T15:00+02:00", "end": "2023-10-12T16:00+02:00", "objectives": [], "vod": null, "schedule": {"items": [{"id": "c7cbfd3a-9961-4cff-bd71-55e61c5c6280", "title": "Table ronde :  Impacts organisationnels des dépistages", "start": "2023-10-12T15:00+02:00", "end": "2023-10-12T16:00+02:00", "speakers": {"items": []}, "vod": {"media": {"type": "VIDEO", "thumbnail": "https://services.medicalcongress.online/congress/medias/2023/JFR-2023/1465/video/thumbs/poster.jpg", "element": {"sources": [{"uri": "https://services.medicalcongress.online/congress/medias/2023/JFR-2023/1465/video/y_1080p_4000kb.mp4"}]}}}}]}}}}